{"meta": {"fps": 30, "horses": 10, "distance": 1600, "markers": [0, 1000, 1600], "note": "高知8R 2026/06/13 公式アンカー自動生成(発走=映像検出, 残600m/ゴール=公式タイム逆算)"}, "records": {"0": {"10": {"t": 17601.667, "x": 0.5, "y": 0.5}, "4": {"t": 17601.667, "x": 0.5, "y": 0.5}, "8": {"t": 17601.667, "x": 0.5, "y": 0.5}, "6": {"t": 17601.667, "x": 0.5, "y": 0.5}, "3": {"t": 17601.667, "x": 0.5, "y": 0.5}, "2": {"t": 17601.667, "x": 0.5, "y": 0.5}, "5": {"t": 17601.667, "x": 0.5, "y": 0.5}, "7": {"t": 17601.667, "x": 0.5, "y": 0.5}, "1": {"t": 17601.667, "x": 0.5, "y": 0.5}, "9": {"t": 17601.667, "x": 0.5, "y": 0.5}}, "1000": {"10": {"t": 17669.467, "x": 0.5, "y": 0.5}, "4": {"t": 17669.967, "x": 0.5, "y": 0.5}, "8": {"t": 17669.967, "x": 0.5, "y": 0.5}, "6": {"t": 17670.167, "x": 0.5, "y": 0.5}, "3": {"t": 17670.267, "x": 0.5, "y": 0.5}, "2": {"t": 17669.667, "x": 0.5, "y": 0.5}, "5": {"t": 17670.167, "x": 0.5, "y": 0.5}, "7": {"t": 17669.567, "x": 0.5, "y": 0.5}, "1": {"t": 17670.167, "x": 0.5, "y": 0.5}, "9": {"t": 17669.767, "x": 0.5, "y": 0.5}}, "1600": {"10": {"t": 17710.367, "x": 0.5, "y": 0.5}, "4": {"t": 17710.967, "x": 0.5, "y": 0.5}, "8": {"t": 17711.567, "x": 0.5, "y": 0.5}, "6": {"t": 17711.567, "x": 0.5, "y": 0.5}, "3": {"t": 17712.167, "x": 0.5, "y": 0.5}, "2": {"t": 17712.567, "x": 0.5, "y": 0.5}, "5": {"t": 17712.567, "x": 0.5, "y": 0.5}, "7": {"t": 17712.867, "x": 0.5, "y": 0.5}, "1": {"t": 17712.967, "x": 0.5, "y": 0.5}, "9": {"t": 17712.967, "x": 0.5, "y": 0.5}}}, "guides": {}, "candidates": {}}